stone_brick/__init__.py
stone_brick/asynclib/__init__.py
stone_brick/asynclib/anyio_utils.py
stone_brick/asynclib/bg_runner.py
stone_brick/asynclib/bwait.py
stone_brick/asynclib/common.py
stone_brick/asynclib/cwait.py
stone_brick/asynclib/iterable_runner.py
stone_brick/asynclib/stream_runner.py
stone_brick/backend/api/login.py
stone_brick/backend/auth/__init__.py
stone_brick/backend/ctx.py
stone_brick/backend/tables/user.py
stone_brick/encryptlib/__init__.py
stone_brick/encryptlib/jwt.py
stone_brick/llm/__init__.py
stone_brick/llm/error.py
stone_brick/llm/events/events.py
stone_brick/llm/events/task_events.py
stone_brick/llm/utils.py
stone_brick/oauth_login/__init__.py
stone_brick/oauth_login/fastapi.py
stone_brick/oauth_login/providers/common.py
stone_brick/oauth_login/providers/google.py
stone_brick/observability/__init__.py
stone_brick/observability/otel_utils.py
stone_brick/parser/__init__.py
stone_brick/parser/xml.py
stone_brick/pydantic_ai_utils.py
stone_brick/retry/__init__.py
stone_brick/retry/utils.py
stone_brick/validate/__init__.py
stone_brick/validate/utils.py
stone_brick_toolkit-0.12.1.dist-info/METADATA
stone_brick_toolkit-0.12.1.dist-info/WHEEL
stone_brick_toolkit-0.12.1.dist-info/entry_points.txt
stone_brick_toolkit-0.12.1.dist-info/RECORD
